example_pkg/__init__.py
example_pkg/code_file.py
my_third_python_package-0.0.1.dist-info/METADATA
my_third_python_package-0.0.1.dist-info/WHEEL
my_third_python_package-0.0.1.dist-info/top_level.txt
my_third_python_package-0.0.1.dist-info/RECORD
