Metadata-Version: 2.1
Name: my-third-python-package
Version: 0.0.1
Summary: My third package in python related to missing values
Home-page: https://github.com/pypa/sampleproject
Author: Parteek Satija
Author-email: psatija_be17@thapar.edu
License: UNKNOWN
Platform: UNKNOWN
Requires-Python: >=3.6
